<?xml version="1.0" encoding="utf-8"?>
<LanguageData>

    <!-- Vanilla Factions Expanded - Vikings --> 
        <VFEV_Facepaint_Barbarian.label>Bárbaro</VFEV_Facepaint_Barbarian.label>
        <VFEV_Facepaint_Beak.label>Bico</VFEV_Facepaint_Beak.label>
        <VFEV_Facepaint_Bear.label>Urso</VFEV_Facepaint_Bear.label>
        <VFEV_Facepaint_Cross.label>Cruz</VFEV_Facepaint_Cross.label>
        <VFEV_Facepaint_Descendant.label>Descendente</VFEV_Facepaint_Descendant.label>
        <VFEV_Facepaint_Eagle.label>Águia</VFEV_Facepaint_Eagle.label>
        <VFEV_Facepaint_Fairy.label>Fada</VFEV_Facepaint_Fairy.label>
        <VFEV_Facepaint_Fighter.label>Lutador</VFEV_Facepaint_Fighter.label>
        <VFEV_Facepaint_Freya.label>Freya</VFEV_Facepaint_Freya.label>
        <VFEV_Facepaint_Godly.label>Piedoso</VFEV_Facepaint_Godly.label>
        <VFEV_Facepaint_Hawk.label>Falcão</VFEV_Facepaint_Hawk.label>
        <VFEV_Facepaint_Hunter.label>Caçador</VFEV_Facepaint_Hunter.label>
        <VFEV_Facepaint_Jarl.label>Guerreiro</VFEV_Facepaint_Jarl.label>
        <VFEV_Facepaint_Keeper.label>Guarda</VFEV_Facepaint_Keeper.label>
        <VFEV_Facepaint_Oracle.label>Oráculo</VFEV_Facepaint_Oracle.label>
        <VFEV_Facepaint_Resident.label>Residente</VFEV_Facepaint_Resident.label>
        <VFEV_Facepaint_Roar.label>Rugido</VFEV_Facepaint_Roar.label>
        <VFEV_Facepaint_Ruler.label>Governador</VFEV_Facepaint_Ruler.label>
        <VFEV_Facepaint_Savage.label>Selvagem</VFEV_Facepaint_Savage.label>
        <VFEV_Facepaint_Sunset.label>Ocaso</VFEV_Facepaint_Sunset.label>
        <VFEV_Facepaint_Tears.label>Pranto</VFEV_Facepaint_Tears.label>
        <VFEV_Facepaint_Widow.label>Viúva</VFEV_Facepaint_Widow.label>

</LanguageData>